[
  {
    "id": 1,
    "category": "BRAND",
    "title": "향기를 처방해드립니다.",
    "desc": "하루종일 긍정적인 몰입을 돕는 안눈치아타 디퓨저 컬렉션 ",
    "img": "https://cdn.perfume-dev.com/curation/1709084041178_240227-curation_th.jpg"
  },
  {
    "id": 2,
    "category": "BRAND",
    "title": "향기를 처방해드립니다.",
    "desc": "하루종일 긍정적인 몰입을 돕는 안눈치아타 디퓨저 컬렉션 ",
    "img": "https://cdn.perfume-dev.com/curation/1709084041178_240227-curation_th.jpg"
  },
  {
    "id": 3,
    "category": "BRAND",
    "title": "향기를 처방해드립니다.",
    "desc": "하루종일 긍정적인 몰입을 돕는 안눈치아타 디퓨저 컬렉션 ",
    "img": "https://cdn.perfume-dev.com/curation/1709084041178_240227-curation_th.jpg"
  }
]
